gamr_backend_service/__init__.py
gamr_backend_service/__main__.py
gamr_backend_service/api/__init__.py
gamr_backend_service/api/factory.py
gamr_backend_service/api/routes/__init__.py
gamr_backend_service/api/routes/base.py
gamr_backend_service/api/routes/exception_handlers.py
gamr_backend_service/auth/__init__.py
gamr_backend_service/auth/exceptions.py
gamr_backend_service/auth/token.py
gamr_backend_service/data/__init__.py
gamr_backend_service/data/user_manager.py
gamr_backend_service/database_connector/__init__.py
gamr_backend_service/database_connector/abstract_database_connector.py
gamr_backend_service/database_connector/firebase.py
gamr_backend_service/model_services/__init__.py
gamr_backend_service/model_services/abstract_model_service.py
gamr_backend_service/model_services/hugging_face/__init__.py
gamr_backend_service/model_services/hugging_face/errors.py
gamr_backend_service/model_services/hugging_face/service.py
gamr_backend_service/models/__init__.py
gamr_backend_service/models/errors.py
gamr_backend_service/models/image_data.py
gamr_backend_service/models/image_response.py
gamr_backend_service/models/user.py
gamr_backend_service/settings.py
gamr_backend_service-1.0.0.dist-info/LICENSE.txt
gamr_backend_service-1.0.0.dist-info/METADATA
gamr_backend_service-1.0.0.dist-info/WHEEL
gamr_backend_service-1.0.0.dist-info/entry_points.txt
gamr_backend_service-1.0.0.dist-info/RECORD
